safari/__init__.py
safari/safari_export.py
safari-1.2.0.dist-info/WHEEL
safari-1.2.0.dist-info/METADATA
safari-1.2.0.dist-info/RECORD
